cli_grid/__init__.py
cli_grid/cli-grid.py
cli_grid-0.0.1.dist-info/LICENCE
cli_grid-0.0.1.dist-info/METADATA
cli_grid-0.0.1.dist-info/WHEEL
cli_grid-0.0.1.dist-info/top_level.txt
cli_grid-0.0.1.dist-info/RECORD
