Metadata-Version: 2.1
Name: cli-grid
Version: 0.0.1
Summary: A simple python package for generating, managing and visualizing grids
Author-email: Sam <samuelayodeji2478@gmail.com>
Project-URL: Homepage, https://github.com/olascoWorks/cli-grid
Project-URL: Issues, https://github.com/olascoWorks/cli-grid/issues
Classifier: Programming Language :: Python :: 3
Classifier: License :: OSI Approved :: MIT License
Classifier: Operating System :: OS Independent
Requires-Python: >=3.8
License-File: LICENCE
